klear/Pretty.py
klear/__init__.py
klear/__main__.py
klear/cli.py
klear/entries.py
klear/klear_client.py
klear/klear_server.py
klear-1.0.0.dist-info/METADATA
klear-1.0.0.dist-info/WHEEL
klear-1.0.0.dist-info/entry_points.txt
klear-1.0.0.dist-info/top_level.txt
klear-1.0.0.dist-info/RECORD
